fir_filter.v
module fir_filter #(
    parameter DATA_WIDTH = 8   // width of input/output samples
)(
    input                               clk,
    input                               rst_n,     // active-low synchronous reset
    input                               valid_in,  // new input sample available
    input  signed [DATA_WIDTH-1:0]      data_in,   // input sample x[n]

    output reg                          valid_out, // output sample available
    output reg  signed [DATA_WIDTH-1:0] data_out   // filtered output y[n]
);

    // ---------------------------------------------------------
    // Fixed filter coefficients
    // ---------------------------------------------------------
    localparam signed [3:0] H0 = 4'sd1;
    localparam signed [3:0] H1 = 4'sd3;
    localparam signed [3:0] H2 = 4'sd3;
    localparam signed [3:0] H3 = 4'sd1;

    // ---------------------------------------------------------
    // History registers: hold x[n-1], x[n-2], x[n-3]
    // (x[n] itself arrives live on data_in this cycle)
    // ---------------------------------------------------------
    reg signed [DATA_WIDTH-1:0] xm1, xm2, xm3;

    // Combinational taps for this cycle's convolution
    wire signed [DATA_WIDTH-1:0] tap0 = data_in; // x[n]
    wire signed [DATA_WIDTH-1:0] tap1 = xm1;     // x[n-1]
    wire signed [DATA_WIDTH-1:0] tap2 = xm2;     // x[n-2]
    wire signed [DATA_WIDTH-1:0] tap3 = xm3;     // x[n-3]

    // Products need extra headroom: DATA_WIDTH + coeff width
    wire signed [DATA_WIDTH+3:0] p0 = tap0 * H0;
    wire signed [DATA_WIDTH+3:0] p1 = tap1 * H1;
    wire signed [DATA_WIDTH+3:0] p2 = tap2 * H2;
    wire signed [DATA_WIDTH+3:0] p3 = tap3 * H3;

    wire signed [DATA_WIDTH+5:0] sum = p0 + p1 + p2 + p3; // guard bits

    // ---------------------------------------------------------
    // Sequential logic: history shift + registered output
    // ---------------------------------------------------------
    always @(posedge clk) begin
        if (!rst_n) begin
            xm1 <= {DATA_WIDTH{1'b0}};
            xm2 <= {DATA_WIDTH{1'b0}};
            xm3 <= {DATA_WIDTH{1'b0}};
            data_out  <= {DATA_WIDTH{1'b0}};
            valid_out <= 1'b0;
        end else begin
            valid_out <= valid_in;   // 1-cycle output latency

            if (valid_in) begin
                // arithmetic right shift by 3 = divide by 8, sign-preserving
                data_out <= sum[DATA_WIDTH+4:3];

                // push history: x[n] becomes x[n-1] next cycle, etc.
                xm3 <= xm2;
                xm2 <= xm1;
                xm1 <= data_in;
            end
        end
    end

endmodule

tb_fir_filter.v
`timescale 1ns / 1ps

module tb_fir_filter;

    localparam DATA_WIDTH = 8;
    localparam CLK_PERIOD = 10;

    reg                          clk;
    reg                          rst_n;
    reg                          valid_in;
    reg  signed [DATA_WIDTH-1:0] data_in;

    wire                         valid_out;
    wire signed [DATA_WIDTH-1:0] data_out;

    integer i;

    // ---------------------------------------------------------
    // DUT instantiation
    // ---------------------------------------------------------
    fir_filter #(
        .DATA_WIDTH(DATA_WIDTH)
    ) dut (
        .clk       (clk),
        .rst_n     (rst_n),
        .valid_in  (valid_in),
        .data_in   (data_in),
        .valid_out (valid_out),
        .data_out  (data_out)
    );

    // ---------------------------------------------------------
    // Clock generation
    // ---------------------------------------------------------
    initial clk = 1'b0;
    always #(CLK_PERIOD/2) clk = ~clk;

    // ---------------------------------------------------------
    // Helper task: apply one sample on the rising edge
    // ---------------------------------------------------------
    task apply_sample(input signed [DATA_WIDTH-1:0] val);
        begin
            @(negedge clk);
            data_in  = val;
            valid_in = 1'b1;
            @(negedge clk);
            valid_in = 1'b0;
        end
    endtask

    // ---------------------------------------------------------
    // Stimulus
    // ---------------------------------------------------------
    initial begin
        $dumpfile("fir_filter.vcd");
        $dumpvars(0, tb_fir_filter);

        rst_n    = 1'b0;
        valid_in = 1'b0;
        data_in  = 0;

        repeat (2) @(negedge clk);
        rst_n = 1'b1;

        $display("time\tx_in\tvalid_in\ty_out\tvalid_out");

        // ---------------- Test 1: Impulse response ----------------
        $display("\n--- Test 1: Impulse response ---");
        apply_sample(8'sd16);   // single impulse of height 16
        repeat (5) apply_sample(8'sd0);

        repeat (2) @(negedge clk);

        // ---------------- Test 2: Step response ----------------
        $display("\n--- Test 2: Step response ---");
        repeat (6) apply_sample(8'sd10);  // constant input of 10

        repeat (2) @(negedge clk);

        // ---------------- Test 3: Oscillating / noisy input ----------------
        $display("\n--- Test 3: Oscillating input (smoothing demo) ---");
        // Alternating +20 / -20 : high-frequency signal that a
        // low-pass FIR should attenuate strongly.
        for (i = 0; i < 8; i = i + 1) begin
            if (i % 2 == 0)
                apply_sample(8'sd20);
            else
                apply_sample(-8'sd20);
        end

        repeat (4) @(negedge clk);
        $display("\nSimulation complete.");
        $finish;
    end

    // ---------------------------------------------------------
    // Monitor
    // ---------------------------------------------------------
    always @(posedge clk) begin
        if (rst_n)
            $display("%0t\t%0d\t%0b\t%0d\t%0b",
                      $time, data_in, valid_in, data_out, valid_out);
    end

endmodule

fir_filter.vcd
$date
	Sun Sep 06 14:37:53 2026
$end
$version
	Icarus Verilog
$end
$timescale
	1ps
$end
$scope module tb_fir_filter $end
$var wire 1 ! valid_out $end
$var wire 8 " data_out [7:0] $end
$var reg 1 # clk $end
$var reg 8 $ data_in [7:0] $end
$var reg 1 % rst_n $end
$var reg 1 & valid_in $end
$var integer 32 ' i [31:0] $end
$scope module dut $end
$var wire 1 # clk $end
$var wire 8 ( data_in [7:0] $end
$var wire 1 % rst_n $end
$var wire 8 ) tap0 [7:0] $end
$var wire 1 & valid_in $end
$var wire 8 * tap3 [7:0] $end
$var wire 8 + tap2 [7:0] $end
$var wire 8 , tap1 [7:0] $end
$var wire 14 - sum [13:0] $end
$var wire 12 . p3 [11:0] $end
$var wire 12 / p2 [11:0] $end
$var wire 12 0 p1 [11:0] $end
$var wire 12 1 p0 [11:0] $end
$var reg 8 2 data_out [7:0] $end
$var reg 1 ! valid_out $end
$var reg 8 3 xm1 [7:0] $end
$var reg 8 4 xm2 [7:0] $end
$var reg 8 5 xm3 [7:0] $end
$upscope $end
$scope task apply_sample $end
$var reg 8 6 val [7:0] $end
$upscope $end
$upscope $end
$enddefinitions $end
#0
$dumpvars
bx 6
bx 5
bx 4
bx 3
bx 2
b0 1
bx 0
bx /
bx .
bx -
bx ,
bx +
bx *
b0 )
b0 (
bx '
0&
0%
b0 $
0#
bx "
x!
$end
#5000
0!
b0 "
b0 2
b0 -
b0 .
b0 *
b0 5
b0 /
b0 +
b0 4
b0 0
b0 ,
b0 3
1#
#10000
0#
#15000
1#
#20000
b10000 6
1%
0#
#25000
1#
#30000
1&
b10000 -
b10000 1
b10000 )
b10000 $
b10000 (
0#
#35000
b1000000 -
b110000 0
b10000 ,
b10000 3
b10 "
b10 2
1!
1#
#40000
b0 6
0&
0#
#45000
0!
1#
#50000
1&
b110000 -
b0 1
b0 )
b0 $
b0 (
0#
#55000
b0 0
b0 ,
b0 3
b110000 -
b110000 /
b10000 +
b10000 4
b110 "
b110 2
1!
1#
#60000
0&
0#
#65000
0!
1#
#70000
1&
0#
#75000
b0 /
b0 +
b0 4
b10000 -
b10000 .
b10000 *
b10000 5
1!
1#
#80000
0&
0#
#85000
0!
1#
#90000
1&
0#
#95000
b0 -
b0 .
b0 *
b0 5
b10 "
b10 2
1!
1#
#100000
0&
0#
#105000
0!
1#
#110000
1&
0#
#115000
b0 "
b0 2
1!
1#
#120000
0&
0#
#125000
0!
1#
#130000
1&
0#
#135000
1!
1#
#140000
0&
0#
#145000
0!
1#
#150000
0#
#155000
1#
#160000
b1010 6
0#
#165000
1#
#170000
1&
b1010 -
b1010 1
b1010 )
b1010 $
b1010 (
0#
#175000
b101000 -
b11110 0
b1010 ,
b1010 3
b1 "
b1 2
1!
1#
#180000
0&
0#
#185000
0!
1#
#190000
1&
0#
#195000
b1000110 -
b11110 /
b1010 +
b1010 4
b101 "
b101 2
1!
1#
#200000
0&
0#
#205000
0!
1#
#210000
1&
0#
#215000
b1010000 -
b1010 .
b1010 *
b1010 5
b1000 "
b1000 2
1!
1#
#220000
0&
0#
#225000
0!
1#
#230000
1&
0#
#235000
b1010 "
b1010 2
1!
1#
#240000
0&
0#
#245000
0!
1#
#250000
1&
0#
#255000
1!
1#
#260000
0&
0#
#265000
0!
1#
#270000
1&
0#
#275000
1!
1#
#280000
0&
0#
#285000
0!
1#
#290000
0#
#295000
1#
#300000
b10100 6
b0 '
0#
#305000
1#
#310000
1&
b1011010 -
b10100 1
b10100 )
b10100 $
b10100 (
0#
#315000
b1111000 -
b111100 0
b10100 ,
b10100 3
b1011 "
b1011 2
1!
1#
#320000
b11101100 6
b1 '
0&
0#
#325000
0!
1#
#330000
1&
b1010000 -
b111111101100 1
b11101100 )
b11101100 $
b11101100 (
0#
#335000
b111111000100 0
b11101100 ,
b11101100 3
b11111111110110 -
b111100 /
b10100 +
b10100 4
b1010 "
b1010 2
1!
1#
#340000
b10100 6
b10 '
0&
0#
#345000
0!
1#
#350000
1&
b11110 -
b10100 1
b10100 )
b10100 $
b10100 (
0#
#355000
b111100 0
b10100 ,
b10100 3
b111111000100 /
b11101100 +
b11101100 4
b101000 -
b10100 .
b10100 *
b10100 5
b11 "
b11 2
1!
1#
#360000
b11101100 6
b11 '
0&
0#
#365000
0!
1#
#370000
1&
b0 -
b111111101100 1
b11101100 )
b11101100 $
b11101100 (
0#
#375000
b111111000100 0
b11101100 ,
b11101100 3
b111100 /
b10100 +
b10100 4
b11111111011000 -
b111111101100 .
b11101100 *
b11101100 5
b0 "
b0 2
1!
1#
#380000
b10100 6
b100 '
0&
0#
#385000
0!
1#
#390000
1&
b0 -
b10100 1
b10100 )
b10100 $
b10100 (
0#
#395000
b111100 0
b10100 ,
b10100 3
b111111000100 /
b11101100 +
b11101100 4
b101000 -
b10100 .
b10100 *
b10100 5
1!
1#
#400000
b11101100 6
b101 '
0&
0#
#405000
0!
1#
#410000
1&
b0 -
b111111101100 1
b11101100 )
b11101100 $
b11101100 (
0#
#415000
b111111000100 0
b11101100 ,
b11101100 3
b111100 /
b10100 +
b10100 4
b11111111011000 -
b111111101100 .
b11101100 *
b11101100 5
1!
1#
#420000
b10100 6
b110 '
0&
0#
#425000
0!
1#
#430000
1&
b0 -
b10100 1
b10100 )
b10100 $
b10100 (
0#
#435000
b111100 0
b10100 ,
b10100 3
b111111000100 /
b11101100 +
b11101100 4
b101000 -
b10100 .
b10100 *
b10100 5
1!
1#
#440000
b11101100 6
b111 '
0&
0#
#445000
0!
1#
#450000
1&
b0 -
b111111101100 1
b11101100 )
b11101100 $
b11101100 (
0#
#455000
b111111000100 0
b11101100 ,
b11101100 3
b111100 /
b10100 +
b10100 4
b11111111011000 -
b111111101100 .
b11101100 *
b11101100 5
1!
1#
#460000
b1000 '
0&
0#
#465000
0!
1#
